remote_table/__init__.py
remote_table/core.py
remote_table-0.1.0.dist-info/WHEEL
remote_table-0.1.0.dist-info/METADATA
remote_table-0.1.0.dist-info/RECORD
