Metadata-Version: 2.4
Name: remote-table
Version: 0.1.0
Summary: A Python port of the remote_table Ruby gem. Reads tabular data from local and remote sources.
Author: Derek Willis
Author-email: Derek Willis <dwillis@gmail.com>
License-Expression: MIT
Requires-Dist: pandas>=2.3.0
Requires-Dist: numpy>=1.25.0
Requires-Dist: requests
Requires-Dist: openpyxl
Requires-Dist: pyyaml
Requires-Dist: beautifulsoup4
Requires-Dist: lxml
Requires-Dist: odfpy
Requires-Dist: build>=1.3.0
Requires-Python: >=3.12
Project-URL: Homepage, https://github.com/dwillis/remote_table
